llmtask/__init__.py
llmtask/_prompt_generator.py
llmtask/_subject_names.py
llmtask/_utils.py
llmtask/error.py
llmtask/datasets/.DS_Store
llmtask/datasets/ceval/.DS_Store
llmtask/datasets/ceval/subject_mapping.json
llmtask/datasets/ceval/dev/accountant_dev.csv
llmtask/datasets/ceval/dev/advanced_mathematics_dev.csv
llmtask/datasets/ceval/dev/art_studies_dev.csv
llmtask/datasets/ceval/dev/basic_medicine_dev.csv
llmtask/datasets/ceval/dev/business_administration_dev.csv
llmtask/datasets/ceval/dev/chinese_language_and_literature_dev.csv
llmtask/datasets/ceval/dev/civil_servant_dev.csv
llmtask/datasets/ceval/dev/clinical_medicine_dev.csv
llmtask/datasets/ceval/dev/college_chemistry_dev.csv
llmtask/datasets/ceval/dev/college_economics_dev.csv
llmtask/datasets/ceval/dev/college_physics_dev.csv
llmtask/datasets/ceval/dev/college_programming_dev.csv
llmtask/datasets/ceval/dev/computer_architecture_dev.csv
llmtask/datasets/ceval/dev/computer_network_dev.csv
llmtask/datasets/ceval/dev/discrete_mathematics_dev.csv
llmtask/datasets/ceval/dev/education_science_dev.csv
llmtask/datasets/ceval/dev/electrical_engineer_dev.csv
llmtask/datasets/ceval/dev/environmental_impact_assessment_engineer_dev.csv
llmtask/datasets/ceval/dev/fire_engineer_dev.csv
llmtask/datasets/ceval/dev/high_school_biology_dev.csv
llmtask/datasets/ceval/dev/high_school_chemistry_dev.csv
llmtask/datasets/ceval/dev/high_school_chinese_dev.csv
llmtask/datasets/ceval/dev/high_school_geography_dev.csv
llmtask/datasets/ceval/dev/high_school_history_dev.csv
llmtask/datasets/ceval/dev/high_school_mathematics_dev.csv
llmtask/datasets/ceval/dev/high_school_physics_dev.csv
llmtask/datasets/ceval/dev/high_school_politics_dev.csv
llmtask/datasets/ceval/dev/ideological_and_moral_cultivation_dev.csv
llmtask/datasets/ceval/dev/law_dev.csv
llmtask/datasets/ceval/dev/legal_professional_dev.csv
llmtask/datasets/ceval/dev/logic_dev.csv
llmtask/datasets/ceval/dev/mao_zedong_thought_dev.csv
llmtask/datasets/ceval/dev/marxism_dev.csv
llmtask-0.0.2.dist-info/LICENSE
llmtask-0.0.2.dist-info/METADATA
llmtask-0.0.2.dist-info/WHEEL
llmtask-0.0.2.dist-info/top_level.txt
llmtask-0.0.2.dist-info/RECORD
