Metadata-Version: 2.1
Name: llmtask
Version: 0.0.2
Summary: LLM Downstream Task Evaluation Tool.
Home-page: 
Author: Slightwind
Author-email: slightwindsec@gmail.com
Classifier: Programming Language :: Python :: 3
License-File: LICENSE
Requires-Dist: tqdm
Requires-Dist: pandas
